LICENSE.txt
MANIFEST.in
setup.py
rxt_backend_base/__init__.py
rxt_backend_base.egg-info/PKG-INFO
rxt_backend_base.egg-info/SOURCES.txt
rxt_backend_base.egg-info/dependency_links.txt
rxt_backend_base.egg-info/requires.txt
rxt_backend_base.egg-info/top_level.txt
rxt_backend_base/es2015/__init__.py
rxt_backend_base/es2015/framing/__init__.py
rxt_backend_base/es2015/framing/newline/__init__.py
rxt_backend_base/es2015/framing/newline/source.content.tpl
rxt_backend_base/es2015/framing/newline/source.footer.tpl
rxt_backend_base/es2015/framing/newline/source.header.tpl
rxt_backend_base/es2015/framing/none/__init__.py
rxt_backend_base/es2015/framing/none/source.content.tpl
rxt_backend_base/es2015/framing/none/source.footer.tpl
rxt_backend_base/es2015/framing/none/source.header.tpl
rxt_backend_base/es2015/serialization/__init__.py
rxt_backend_base/es2015/serialization/json/__init__.py
rxt_backend_base/es2015/serialization/json/source.content.tpl
rxt_backend_base/es2015/serialization/json/source.footer.tpl
rxt_backend_base/es2015/serialization/json/source.header.tpl
rxt_backend_base/es2015/stream/__init__.py
rxt_backend_base/es2015/stream/source.content.tpl
rxt_backend_base/es2015/stream/source.footer.tpl
rxt_backend_base/es2015/stream/source.header.tpl
rxt_backend_base/es2015_rxjs/__init__.py
rxt_backend_base/es2015_rxjs/stream/__init__.py
rxt_backend_base/es2015_rxjs/stream/source.content.tpl
rxt_backend_base/es2015_rxjs/stream/source.footer.tpl
rxt_backend_base/es2015_rxjs/stream/source.header.tpl
rxt_backend_base/python3/__init__.py
rxt_backend_base/python3/framing/__init__.py
rxt_backend_base/python3/framing/newline/__init__.py
rxt_backend_base/python3/framing/newline/source.content.tpl
rxt_backend_base/python3/framing/newline/source.footer.tpl
rxt_backend_base/python3/framing/newline/source.header.tpl
rxt_backend_base/python3/serialization/__init__.py
rxt_backend_base/python3/serialization/json/__init__.py
rxt_backend_base/python3/serialization/json/source.content.tpl
rxt_backend_base/python3/serialization/json/source.footer.tpl
rxt_backend_base/python3/serialization/json/source.header.tpl
rxt_backend_base/python3/stream/__init__.py
