Metadata-Version: 1.1
Name: rxt-backend-base
Version: 0.4.0
Summary: Base backend for RxTender
Home-page: https://github.com/rxtender/rxt-backend-base
Author: Romain Picard
Author-email: romain.picard@oakbits.com
License: MIT
Platform: any
Classifier: Development Status :: 3 - Alpha
Classifier: License :: OSI Approved :: MIT License
Classifier: Intended Audience :: Developers
Classifier: Programming Language :: Python :: 3
Classifier: Topic :: Software Development :: Debuggers
